src/my_package/__init__.py
src/my_package/addonethousend1.py
addonethousend-0.0.2.dist-info/METADATA
addonethousend-0.0.2.dist-info/WHEEL
addonethousend-0.0.2.dist-info/licenses/LICENSE
addonethousend-0.0.2.dist-info/RECORD
