Metadata-Version: 2.1
Name: addonethousend
Version: 0.0.2
Summary: Add One Thousend package
Project-URL: Homepage, https://github.com/pypa/addonethousend
Project-URL: Bug Tracker, https://github.com/pypa/addonethousend/issues
Author-email: powly535 <shyamkrishnanpv535lenovo@gmail.com>
License-File: LICENSE
Classifier: License :: OSI Approved :: MIT License
Classifier: Operating System :: OS Independent
Classifier: Programming Language :: Python :: 3
Requires-Python: >=3.7
